<?xml version="1.0" encoding="UTF-8"?>
<!DOCTYPE patent-application-publication SYSTEM "dtd_conversion.dtd" >
<patent-application-publication>
  <subdoc-bibliographic-information>
    <document-id>
      <doc-number>doc-number</doc-number>
      <kind-code>kind-code</kind-code>
      <document-date>document-date</document-date>
      <country-code>country-code</country-code>
    </document-id>
    <publication-filing-type>publication-filing-type</publication-filing-type>
    <domestic-filing-data>
      <application-number>
        <doc-number>doc-number</doc-number>
      </application-number>
      <application-number-series-code>application-number-series-code</application-number-series-code>
      <filing-date>filing-date</filing-date>
      <continued-prosecution-application-flag/>
      <rule-47-flag/>
    </domestic-filing-data>
    <foreign-priority-data>
      <priority-application-number>
        <doc-number>doc-number</doc-number>
      </priority-application-number>
      <filing-date>filing-date</filing-date>
      <country-code>country-code</country-code>
    </foreign-priority-data>
    <technical-information>
      <classification-ipc>
        <classification-ipc-primary>
          <ipc>ipc</ipc>
        </classification-ipc-primary>
        <classification-ipc-secondary>
          <ipc>ipc</ipc>
        </classification-ipc-secondary>
        <classification-ipc-edition>classification-ipc-edition</classification-ipc-edition>
      </classification-ipc>
      <classification-us>
        <classification-us-primary>
          <uspc>
            <class>class</class>
            <subclass>subclass</subclass>
          </uspc>
        </classification-us-primary>
        <classification-us-secondary>
          <uspc>
            <class>class</class>
            <subclass>subclass</subclass>
          </uspc>
        </classification-us-secondary>
      </classification-us>
      <title-of-invention/>
      <botanic>
        <latin-name>latin-name</latin-name>
        <variety>variety</variety>
      </botanic>
      <citation>
        <cited-patent-literature>
          <document-id>
            <doc-number>doc-number</doc-number>
            <kind-code>kind-code</kind-code>
            <document-date>document-date</document-date>
            <country-code>country-code</country-code>
          </document-id>
          <party>
            <name>
              <name-prefix>name-prefix</name-prefix>
              <given-name>given-name</given-name>
              <middle-name>middle-name</middle-name>
              <family-name>family-name</family-name>
              <name-suffix>name-suffix</name-suffix>
            </name>
            <organization-name>organization-name</organization-name>
            <address>
              <military-address>military-address</military-address>
              <address-1>address-1</address-1>
              <address-2>address-2</address-2>
              <city>city</city>
              <state>state</state>
              <postalcode>postalcode</postalcode>
              <country>
                <country-code>country-code</country-code>
              </country>
              <email>email</email>
              <telephone>telephone</telephone>
              <fax>fax</fax>
            </address>
          </party>
          <classification-ipc>
            <classification-ipc-primary>
              <ipc>ipc</ipc>
            </classification-ipc-primary>
            <classification-ipc-secondary>
              <ipc>ipc</ipc>
            </classification-ipc-secondary>
            <classification-ipc-edition>classification-ipc-edition</classification-ipc-edition>
          </classification-ipc>
          <classification-us>
            <classification-us-primary>
              <uspc>
                <class>class</class>
                <subclass>subclass</subclass>
              </uspc>
            </classification-us-primary>
            <classification-us-secondary>
              <uspc>
                <class>class</class>
                <subclass>subclass</subclass>
              </uspc>
            </classification-us-secondary>
          </classification-us>
        </cited-patent-literature>
        <relevant-section>relevant-section</relevant-section>
      </citation>
    </technical-information>
    <continuity-data>
      <division-of>
        <parent-child>
          <child>
            <document-id>
              <doc-number>doc-number</doc-number>
              <kind-code>kind-code</kind-code>
              <document-date>document-date</document-date>
              <country-code>country-code</country-code>
            </document-id>
          </child>
          <parent>
            <document-id>
              <doc-number>doc-number</doc-number>
              <kind-code>kind-code</kind-code>
              <document-date>document-date</document-date>
              <country-code>country-code</country-code>
            </document-id>
          </parent>
          <parent-status>parent-status</parent-status>
          <parent-patent>
            <document-id>
              <doc-number>doc-number</doc-number>
              <kind-code>kind-code</kind-code>
              <document-date>document-date</document-date>
              <country-code>country-code</country-code>
            </document-id>
          </parent-patent>
        </parent-child>
        <parent-pct>
          <document-id>
            <doc-number>doc-number</doc-number>
            <kind-code>kind-code</kind-code>
            <document-date>document-date</document-date>
            <country-code>country-code</country-code>
          </document-id>
        </parent-pct>
      </division-of>
    </continuity-data>
    <prior-publication>
      <document-id>
        <doc-number>doc-number</doc-number>
        <kind-code>kind-code</kind-code>
        <document-date>document-date</document-date>
        <country-code>country-code</country-code>
      </document-id>
    </prior-publication>
    <inventors>
      <first-named-inventor>
        <name>
          <name-prefix>name-prefix</name-prefix>
          <given-name>given-name</given-name>
          <middle-name>middle-name</middle-name>
          <family-name>family-name</family-name>
          <name-suffix>name-suffix</name-suffix>
        </name>
        <address>
          <military-address>military-address</military-address>
          <address-1>address-1</address-1>
          <address-2>address-2</address-2>
          <city>city</city>
          <state>state</state>
          <postalcode>postalcode</postalcode>
          <country>
            <country-code>country-code</country-code>
          </country>
          <email>email</email>
          <telephone>telephone</telephone>
          <fax>fax</fax>
        </address>
        <residence>
          <military-service>military-service</military-service>
        </residence>
        <authority-applicant>authority-applicant</authority-applicant>
      </first-named-inventor>
    </inventors>
    <assignee>
      <name>
        <name-prefix>name-prefix</name-prefix>
        <given-name>given-name</given-name>
        <middle-name>middle-name</middle-name>
        <family-name>family-name</family-name>
        <name-suffix>name-suffix</name-suffix>
      </name>
      <organization-name>organization-name</organization-name>
      <address>
        <military-address>military-address</military-address>
        <address-1>address-1</address-1>
        <address-2>address-2</address-2>
        <city>city</city>
        <state>state</state>
        <postalcode>postalcode</postalcode>
        <country>
          <country-code>country-code</country-code>
        </country>
        <email>email</email>
        <telephone>telephone</telephone>
        <fax>fax</fax>
      </address>
      <assignee-type>assignee-type</assignee-type>
    </assignee>
    <correspondence-address>
      <name-1>name-1</name-1>
      <name-2>name-2</name-2>
      <address>
        <military-address>military-address</military-address>
        <address-1>address-1</address-1>
        <address-2>address-2</address-2>
        <city>city</city>
        <state>state</state>
        <postalcode>postalcode</postalcode>
        <country>
          <country-code>country-code</country-code>
        </country>
        <email>email</email>
        <telephone>telephone</telephone>
        <fax>fax</fax>
      </address>
    </correspondence-address>
    <international-conventions>
      <pct-application>
        <document-id>
          <doc-number>doc-number</doc-number>
          <kind-code>kind-code</kind-code>
          <document-date>document-date</document-date>
          <country-code>country-code</country-code>
        </document-id>
      </pct-application>
      <usc371-date>usc371-date</usc371-date>
      <usc102e-date>usc102e-date</usc102e-date>
      <pct-publication>
        <document-id>
          <doc-number>doc-number</doc-number>
          <kind-code>kind-code</kind-code>
          <document-date>document-date</document-date>
          <country-code>country-code</country-code>
        </document-id>
      </pct-publication>
    </international-conventions>
    <appendix-data>
      <object-reference id="idvalue0">
        <object-description>object-description</object-description>
        <object-id>object-id</object-id>
        <object-contents>object-contents</object-contents>
      </object-reference>
    </appendix-data>
  </subdoc-bibliographic-information>
  <subdoc-abstract>
    <heading/>
  </subdoc-abstract>
  <subdoc-description>
    <copyright-statement id="idvalue1">
      <heading/>
    </copyright-statement>
    <cross-reference-to-related-applications>
      <heading/>
    </cross-reference-to-related-applications>
    <federal-research-statement>
      <heading/>
      <paragraph-federal-research-statement id="idvalue2"/>
    </federal-research-statement>
    <background-of-invention>
      <heading/>
    </background-of-invention>
    <summary-of-invention>
      <heading/>
    </summary-of-invention>
    <brief-description-of-drawings>
      <heading/>
    </brief-description-of-drawings>
    <brief-description-of-sequences>
      <heading/>
    </brief-description-of-sequences>
    <detailed-description>
      <biological-deposit id="idvalue3">
        <number>number</number>
        <deposit-date>deposit-date</deposit-date>
        <deposit-term>deposit-term</deposit-term>
        <depository>
          <organization-name>organization-name</organization-name>
          <address>
            <military-address>military-address</military-address>
            <address-1>address-1</address-1>
            <address-2>address-2</address-2>
            <city>city</city>
            <state>state</state>
            <postalcode>postalcode</postalcode>
            <country>
              <country-code>country-code</country-code>
            </country>
            <email>email</email>
            <telephone>telephone</telephone>
            <fax>fax</fax>
          </address>
        </depository>
        <deposit-accession-number>deposit-accession-number</deposit-accession-number>
        <deposit-description>deposit-description</deposit-description>
      </biological-deposit>
      <heading/>
    </detailed-description>
    <program-listing-deposit id="idvalue4">
      <heading/>
      <number>number</number>
      <program-listing id="idvalue5">program-listing</program-listing>
    </program-listing-deposit>
  </subdoc-description>
  <sequence-cwu id="idvalue6">
    <number>number</number>
    <sequence-list-old-rules>
      <s-1>
        <s-1-iii>s-1-iii</s-1-iii>
        <s-1-iv>
          <party>
            <name>
              <name-prefix>name-prefix</name-prefix>
              <given-name>given-name</given-name>
              <middle-name>middle-name</middle-name>
              <family-name>family-name</family-name>
              <name-suffix>name-suffix</name-suffix>
            </name>
            <organization-name>organization-name</organization-name>
            <address>
              <military-address>military-address</military-address>
              <address-1>address-1</address-1>
              <address-2>address-2</address-2>
              <city>city</city>
              <state>state</state>
              <postalcode>postalcode</postalcode>
              <country>
                <country-code>country-code</country-code>
              </country>
              <email>email</email>
              <telephone>telephone</telephone>
              <fax>fax</fax>
            </address>
          </party>
        </s-1-iv>
        <s-1-v>
          <s-1-v-a>s-1-v-a</s-1-v-a>
          <s-1-v-b>s-1-v-b</s-1-v-b>
          <s-1-v-c>s-1-v-c</s-1-v-c>
          <s-1-v-d>s-1-v-d</s-1-v-d>
        </s-1-v>
        <s-1-viii>
          <s-1-viii-a>
            <name>
              <name-prefix>name-prefix</name-prefix>
              <given-name>given-name</given-name>
              <middle-name>middle-name</middle-name>
              <family-name>family-name</family-name>
              <name-suffix>name-suffix</name-suffix>
            </name>
          </s-1-viii-a>
          <s-1-viii-b>s-1-viii-b</s-1-viii-b>
          <s-1-viii-c>s-1-viii-c</s-1-viii-c>
        </s-1-viii>
        <s-1-ix>
          <s-1-ix-a>
            <telephone>telephone</telephone>
          </s-1-ix-a>
          <s-1-ix-b>s-1-ix-b</s-1-ix-b>
          <s-1-ix-c>s-1-ix-c</s-1-ix-c>
        </s-1-ix>
      </s-1>
      <s-2 seq-no="">
        <s-2-i>
          <s-2-i-a>s-2-i-a</s-2-i-a>
          <s-2-i-b>s-2-i-b</s-2-i-b>
          <s-2-i-c>s-2-i-c</s-2-i-c>
          <s-2-i-d>s-2-i-d</s-2-i-d>
        </s-2-i>
        <s-2-ii>
          <s-2-ii-mt>s-2-ii-mt</s-2-ii-mt>
          <s-2-ii-a>s-2-ii-a</s-2-ii-a>
        </s-2-ii>
        <s-2-iii>s-2-iii</s-2-iii>
        <s-2-iv>s-2-iv</s-2-iv>
        <s-2-v>s-2-v</s-2-v>
        <s-2-vi>
          <s-2-vi-a>s-2-vi-a</s-2-vi-a>
          <s-2-vi-b>s-2-vi-b</s-2-vi-b>
          <s-2-vi-c>s-2-vi-c</s-2-vi-c>
          <s-2-vi-d>s-2-vi-d</s-2-vi-d>
          <s-2-vi-e>s-2-vi-e</s-2-vi-e>
          <s-2-vi-f>s-2-vi-f</s-2-vi-f>
          <s-2-vi-g>s-2-vi-g</s-2-vi-g>
          <s-2-vi-h>s-2-vi-h</s-2-vi-h>
          <s-2-vi-i>s-2-vi-i</s-2-vi-i>
        </s-2-vi>
        <s-2-vii>
          <s-2-vii-a>s-2-vii-a</s-2-vii-a>
          <s-2-vii-b>s-2-vii-b</s-2-vii-b>
        </s-2-vii>
        <s-2-viii>
          <s-2-viii-a>s-2-viii-a</s-2-viii-a>
          <s-2-viii-b>s-2-viii-b</s-2-viii-b>
          <s-2-viii-c>s-2-viii-c</s-2-viii-c>
        </s-2-viii>
        <s-2-ix>
          <s-2-ix-a>s-2-ix-a</s-2-ix-a>
          <s-2-ix-b>s-2-ix-b</s-2-ix-b>
          <s-2-ix-c>s-2-ix-c</s-2-ix-c>
          <s-2-ix-d>s-2-ix-d</s-2-ix-d>
        </s-2-ix>
        <s-2-x>
          <s-2-x-a>
            <name>
              <name-prefix>name-prefix</name-prefix>
              <given-name>given-name</given-name>
              <middle-name>middle-name</middle-name>
              <family-name>family-name</family-name>
              <name-suffix>name-suffix</name-suffix>
            </name>
          </s-2-x-a>
          <s-2-x-b>s-2-x-b</s-2-x-b>
          <s-2-x-c>s-2-x-c</s-2-x-c>
          <s-2-x-d>s-2-x-d</s-2-x-d>
          <s-2-x-e>s-2-x-e</s-2-x-e>
          <s-2-x-f>s-2-x-f</s-2-x-f>
          <s-2-x-g/>
          <s-2-x-h>
            <doc-number>doc-number</doc-number>
          </s-2-x-h>
          <s-2-x-i>
            <date>date</date>
          </s-2-x-i>
          <s-2-x-j>
            <date>date</date>
          </s-2-x-j>
          <s-2-x-k>s-2-x-k</s-2-x-k>
        </s-2-x>
        <s-2-xi>s-2-xi</s-2-xi>
      </s-2>
    </sequence-list-old-rules>
    <image file="entity" id="idvalue7"/>
  </sequence-cwu>
  <subdoc-claims>
    <heading/>
    <claim id="idvalue8">
      <claim-text/>
    </claim>
  </subdoc-claims>
  <subdoc-drawings id="idvalue9">
    <heading/>
    <representative-figure>representative-figure</representative-figure>
    <figure id="idvalue10"/>
  </subdoc-drawings>
</patent-application-publication>
